mqtt_client_ex/__init__.pyc
mqtt_client_ex/__init__.pyi
mqtt_client_ex/_mqtt_client_ex.pyc
mqtt_client_ex/_mqtt_client_ex.pyi
wh_mqtt_client_ex-0.1.1.dist-info/METADATA
wh_mqtt_client_ex-0.1.1.dist-info/WHEEL
wh_mqtt_client_ex-0.1.1.dist-info/top_level.txt
wh_mqtt_client_ex-0.1.1.dist-info/RECORD
