Metadata-Version: 2.2
Name: wh_mqtt_client_ex
Version: 0.1.1
Summary: A MQTT library Wrapper
Home-page: https://github.com/kanbang/mqtt_client_ex
Author: kanbang
Author-email: kanbang@163.com
Project-URL: Bug Reports, https://github.com/kanbang/mqtt_client_ex/issues
Project-URL: Source, https://github.com/kanbang/mqtt_client_ex
Keywords: mqtt,mqtt-rpc,mqtt_client_ex,paho-mqtt
Classifier: Development Status :: 3 - Alpha
Classifier: Intended Audience :: Developers
Classifier: License :: OSI Approved :: MIT License
Classifier: Operating System :: OS Independent
Classifier: Programming Language :: Python :: 3.9
Classifier: Programming Language :: Python :: 3.10
Classifier: Programming Language :: Python :: 3.11
Classifier: Programming Language :: Python :: 3.12
Classifier: Programming Language :: Python :: 3.13
Requires-Python: >=3.9
Requires-Dist: paho-mqtt>=2.1.0
Dynamic: author
Dynamic: author-email
Dynamic: classifier
Dynamic: description
Dynamic: description-content-type
Dynamic: home-page
Dynamic: keywords
Dynamic: project-url
Dynamic: requires-dist
Dynamic: requires-python
Dynamic: summary
